etielle/__init__.py
etielle/core.py
etielle/executor.py
etielle/fluent.py
etielle/instances.py
etielle/py.typed
etielle/relationships.py
etielle/telemetry.py
etielle/transforms.py
etielle/utils.py
etielle/adapters/supabase_adapter.py
etielle-3.6.1.dist-info/METADATA
etielle-3.6.1.dist-info/WHEEL
etielle-3.6.1.dist-info/RECORD
