Metadata-Version: 2.4
Name: etielle
Version: 3.6.1
Summary: A declarative, type-safe Python DSL for mapping complex nested JSON to relational database schemas
Requires-Python: >=3.13
Provides-Extra: sqlalchemy
Requires-Dist: sqlalchemy>=2.0.0; extra == 'sqlalchemy'
Provides-Extra: sqlmodel
Requires-Dist: sqlmodel>=0.0.27; extra == 'sqlmodel'
Provides-Extra: supabase
Requires-Dist: supabase>=2.0.0; extra == 'supabase'
